httplib2-stubs/METADATA.toml
httplib2-stubs/__init__.pyi
httplib2-stubs/auth.pyi
httplib2-stubs/certs.pyi
httplib2-stubs/error.pyi
httplib2-stubs/iri2uri.pyi
httplib2-stubs/py.typed
types_httplib2-0.31.2.20260125.dist-info/licenses/LICENSE
types_httplib2-0.31.2.20260125.dist-info/METADATA
types_httplib2-0.31.2.20260125.dist-info/WHEEL
types_httplib2-0.31.2.20260125.dist-info/top_level.txt
types_httplib2-0.31.2.20260125.dist-info/RECORD
